ansible_tower_mcp/__init__.py
ansible_tower_mcp/__main__.py
ansible_tower_mcp/ansible_tower_agent.py
ansible_tower_mcp/ansible_tower_api.py
ansible_tower_mcp/ansible_tower_mcp.py
ansible_tower_mcp/mcp_config.json
ansible_tower_mcp/middlewares.py
ansible_tower_mcp/utils.py
ansible_tower_mcp/skills/ansible-tower-mcp-ad-hoc-commands/SKILL.md
ansible_tower_mcp/skills/ansible-tower-mcp-credentials/SKILL.md
ansible_tower_mcp/skills/ansible-tower-mcp-groups/SKILL.md
ansible_tower_mcp/skills/ansible-tower-mcp-hosts/SKILL.md
ansible_tower_mcp/skills/ansible-tower-mcp-inventory/SKILL.md
ansible_tower_mcp/skills/ansible-tower-mcp-job-templates/SKILL.md
ansible_tower_mcp/skills/ansible-tower-mcp-jobs/SKILL.md
ansible_tower_mcp/skills/ansible-tower-mcp-organizations/SKILL.md
ansible_tower_mcp/skills/ansible-tower-mcp-projects/SKILL.md
ansible_tower_mcp/skills/ansible-tower-mcp-schedules/SKILL.md
ansible_tower_mcp/skills/ansible-tower-mcp-system/SKILL.md
ansible_tower_mcp/skills/ansible-tower-mcp-teams/SKILL.md
ansible_tower_mcp/skills/ansible-tower-mcp-users/SKILL.md
ansible_tower_mcp/skills/ansible-tower-mcp-workflow-jobs/SKILL.md
ansible_tower_mcp/skills/ansible-tower-mcp-workflow-templates/SKILL.md
ansible_tower_mcp-1.2.26.dist-info/licenses/LICENSE
scripts/validate_a2a_agent.py
ansible_tower_mcp-1.2.26.dist-info/METADATA
ansible_tower_mcp-1.2.26.dist-info/WHEEL
ansible_tower_mcp-1.2.26.dist-info/entry_points.txt
ansible_tower_mcp-1.2.26.dist-info/top_level.txt
ansible_tower_mcp-1.2.26.dist-info/RECORD
